Workbook

Sheet cover page
A2: Integrated Financial Model & DCF Valuation
A4: Britannia Industries Ltd.
A7: Project Objective
A8: To develop an integrated three-statement financial model for Britannia Industries Ltd.
A9: using historical financial data and estimate the company's intrinsic value through Discounted Cash Flow (DCF) valuation to support investment decision-making.
A12: Financial Period | H12: Tools & Techniques | M12: Key Deliverables
A13: Historical Data: FY2020 – FY2025 | H13: Microsoft Excel | M13: Historical Financial Analysis
A14: Forecast Period: FY2026 – FY2030 | H14: Financial Statement Analysis | M14: Forecasted Financial Statements
H15: Three-Statement Financial Modelling | M15: Integrated Three-Statement Financial Model
H16: Financial Forecasting | M16: Free Cash Flow (FCF) Estimation
A17: Model Components | H17: Discounted Cash Flow (DCF) Valuation | M17: Enterprise Value & Equity Valuation
A18: Assumptions | M18: Intrinsic Share Price Estimation
A19: Income Statement | M19: Market Price Comparison
A20: Balance Sheet
A21: Cash Flow Statement
A22: DCF Valuation

Sheet Assumptions
A3: Assumptions
A4: revenue growth % | C4: 0.09
A5: COGS % of Revenue | C5: 0.53
A6: Employee Expense % of Revenue | C6: 0.04
A7: Other Expense % of Revenue | C7: 0.2
A8: Depreciation % of Revenue | C8: 0.02
A9: Tax Rate % | C9: 0.2
A10: Capex % | C10: 0.03
A11: Change In Working Capital % | C11: 0.02
A12: WACC | C12: 0.1
A13: g | C13: 0.04
A14: Receivable Days | C14: 9
A15: Inventory Days | C15: 43
A16: Payable Days | C16: 60

Sheet Income Statement
A1: BRITANNIA INDUSTRIES
D2: FY 2020 | E2: FY 2021 | F2: FY 2022 | G2: FY 2023 | H2: FY 2024 | I2: FY 2025 | J2: FY 2026 | K2: FY 2027 | L2: FY 2028 | M2: FY 2029 | N2: FY 2030
A3: PROFIT & LOSS | D3: 43921 | E3: 44286 | F3: 44651 | G3: 45016 | H3: 45382 | I3: 45747 | J3: 46112 | K3: 46477 | L3: 46843 | M3: 47208 | N3: 47573
A5: Revenue | D5: 11443.99 | E5: 12883.04 | F5: 13944.67 | G5: 15984.9 | H5: 16546.21 | I5: 17535.02 | J5: =I5*(1+J6) -> 18762.471 | K5: =J5*(1+K6) -> 20075.844 | L5: =K5*(1+L6) -> 21681.912 | M5: =L5*(1+M6) -> 23633.284 | N5: =M5*(1+N6) -> 25760.28
A6: Revenue Growth % | E6: =E5/D5-1 -> 0.12574723 | F6: =F5/E5-1 -> 0.08240524 | G6: =G5/F5-1 -> 0.14630895 | H6: =H5/G5-1 -> 0.035115015 | I6: =I5/H5-1 -> 0.059760513 | J6: 0.07 | K6: 0.07 | L6: 0.08 | M6: 0.09 | N6: 0.09
A7: (-) COGS | D7: 5901.16 | E7: 6502.33 | F7: 7473.97 | G7: 8326.7 | H7: 8546.89 | I7: 9859.45 | J7: =J5*J8 -> 9944.1098 | K7: =K5*K8 -> 10640.198 | L7: =L5*L8 -> 11491.413 | M7: =M5*M8 -> 12525.641 | N7: =N5*N8 -> 13652.948
A8: COGS % | D8: =D7/D5 -> 0.51565582 | E8: =E7/E5 -> 0.50472016 | F8: =F7/F5 -> 0.53597324 | G8: =G7/G5 -> 0.52091036 | H8: =H7/H5 -> 0.51654669 | I8: =I7/I5 -> 0.56227196 | J8: 0.53 | K8: 0.53 | L8: 0.53 | M8: 0.53 | N8: 0.53
A9: Gross Profit | D9: =D5-D7 -> 5542.83 | E9: =E5-E7 -> 6380.71 | F9: =F5-F7 -> 6470.7 | G9: =G5-G7 -> 7658.2 | H9: =H5-H7 -> 7999.32 | I9: =I5-I7 -> 7675.57 | J9: =J5-J7 -> 8818.3616 | K9: =K5-K7 -> 9435.6469 | ... N9: =N5-N7 -> 12107.331
A11: (-) Employee Expense | D11: 486.69 | E11: 527.38 | F11: 542.26 | G11: 658.38 | H11: 708.7 | I11: 704.59 | J11: =J5*J12 -> 750.49886 | K11: =K5*K12 -> 803.03378 | L11: =L5*L12 -> 867.27648 | M11: =M5*M12 -> 945.33136 | N11: =N5*N12 -> 1030.4112
A12: Employee Expense % | D12: =D11/D5 -> 0.042527999 | E12: =E11/E5 -> 0.04093599 | F12: =F11/F5 -> 0.038886542 | G12: =G11/G5 -> 0.041187621 | H12: =H11/H5 -> 0.042831561 | I12: =I11/I5 -> 0.040181876 | J12: 0.04 | K12: 0.04 | L12: 0.04 | M12: 0.04 | N12: 0.04
A13: (-) Other Expense | D13: 2342.21 | E13: 2473.37 | F13: 2632.19 | G13: 3219.96 | H13: 3398.7 | I13: 3446.88 | J13: =J5*J14 -> 3752.4943 | K13: =K5*K14 -> 4015.1689 | L13: =L5*L14 -> 4336.3824 | M13: =M5*M14 -> 4726.6568 | N13: =N5*N14 -> 5152.0559
A14: Other Expense % | D14: =D13/D5 -> 0.20466725 | E14: =E13/E5 -> 0.19198652 | F14: =F13/F5 -> 0.18875958 | G14: =G13/G5 -> 0.20143761 | H14: =H13/H5 -> 0.20540656 | I14: =I13/I5 -> 0.1965712 | J14: 0.2 | K14: 0.2 | L14: 0.2 | M14: 0.2 | N14: 0.2
A15: EBITDA | D15: =D9-D11-D13 -> 2713.93 | E15: =E9-E11-E13 -> 3379.96 | F15: =F9-F11-F13 -> 3296.25 | G15: =G9-G11-G13 -> 3779.86 | H15: =H9-H11-H13 -> 3891.92 | I15: =I9-I11-I13 -> 3524.1 | J15: =J9-J11-J13 -> 4315.3684 | K15: =K9-K11-K13 -> 4617.4442 | ... N15: =N9-N11-N13 -> 5924.8643
A16: EBITDA Margin % | D16: =D15/D5 -> 0.23714893 | E16: =E15/E5 -> 0.26235733 | F16: =F15/F5 -> 0.23638064 | G16: =G15/G5 -> 0.23646441 | H16: =H15/H5 -> 0.23521519 | I16: =I15/I5 -> 0.20097496 | J16: =J15/J5 -> 0.23 | K16: =K15/K5 -> 0.23 | ... N16: =N15/N5 -> 0.23
A18: (-) Depreciation | D18: 184.81 | E18: 197.85 | F18: 200.54 | G18: 225.91 | H18: 300.46 | I18: 313.34 | J18: =J5*J19 -> 375.24943 | K18: =K5*K19 -> 401.51689 | L18: =L5*L19 -> 433.63824 | M18: =M5*M19 -> 472.66568 | N18: =N5*N19 -> 515.20559
A19: Depreciation % | D19: =D18/D5 -> 0.016149088 | E19: =E18/E5 -> 0.0153574 | F19: =F18/F5 -> 0.014381122 | G19: =G18/G5 -> 0.014132713 | H19: =H18/H5 -> 0.018158841 | I19: =I18/I5 -> 0.017869384 | J19: 0.02 | K19: 0.02 | L19: 0.02 | M19: 0.02 | N19: 0.02
A20: EBIT | D20: =D15-D18 -> 2529.12 | E20: =E15-E18 -> 3182.11 | F20: =F15-F18 -> 3095.71 | G20: =G15-G18 -> 3553.95 | H20: =H15-H18 -> 3591.46 | I20: =I15-I18 -> 3210.76 | J20: =J15-J18 -> 3940.119 | K20: =K15-K18 -> 4215.9273 | ... N20: =N15-N18 -> 5409.6587
A21: EBIT Margin % | D21: =D20/D5 -> 0.22099984 | E21: =E20/E5 -> 0.24699993 | F21: =F20/F5 -> 0.22199952 | G21: =G20/G5 -> 0.2223317 | H21: =H20/H5 -> 0.21705635 | I21: =I20/I5 -> 0.18310558 | J21: =J20/J5 -> 0.21 | K21: =K20/K5 -> 0.21 | ... N21: =N20/N5 -> 0.21
A23: (-) Tax | D23: 450.7 | E23: 663.02 | F23: 562.35 | G23: 716.45 | H23: 779.25 | I23: 748.71 | J23: =J20*J24 -> 788.0238 | K23: =K20*K24 -> 843.18546 | L23: =L20*L24 -> 910.6403 | M23: =M20*M24 -> 992.59793 | N23: =N20*N24 -> 1081.9317
A24: Tax Margin % | D24: =D23/D20 -> 0.17820428 | E24: =E23/E20 -> 0.2083586 | F24: =F23/F20 -> 0.18165461 | G24: =G23/G20 -> 0.20159259 | H24: =H23/H20 -> 0.21697304 | I24: =I23/I20 -> 0.23318778 | J24: 0.2 | K24: 0.2 | L24: 0.2 | M24: 0.2 | N24: 0.2
A25: PAT (Net Income) | D25: =D20-D23 -> 2078.42 | E25: =E20-E23 -> 2519.09 | F25: =F20-F23 -> 2533.36 | G25: =G20-G23 -> 2837.5 | H25: =H20-H23 -> 2812.21 | I25: =I20-I23 -> 2462.05 | J25: =J20-J23 -> 3152.0952 | K25: =K20-K23 -> 3372.7419 | ... N25: =N20-N23 -> 4327.727
A26: PAT Margin % | D26: =D25/D5 -> 0.18161673 | E26: =E25/E5 -> 0.19553537 | F26: =F25/F5 -> 0.18167228 | G26: =G25/G5 -> 0.17751128 | H26: =H25/H5 -> 0.16996098 | I26: =I25/I5 -> 0.1404076 | J26: =J25/J5 -> 0.168 | K26: =K25/K5 -> 0.168 | ... N26: =N25/N5 -> 0.168

Sheet Cash Flow
D2: FY 2020 | E2: FY 2021 | F2: FY 2022 | G2: FY 2023 | H2: FY 2024 | I2: FY 2025 | J2: FY 2026 | K2: FY 2027 | L2: FY 2028 | M2: FY 2029 | N2: FY 2030
A3: CASH FLOW | D3: 43921 | E3: 44286 | F3: 44651 | G3: 45016 | H3: 45382 | I3: 45747 | J3: 46112 | K3: 46477 | L3: 46843 | M3: 47208 | N3: 47573
A5: Opening Cash
A7: PAT (Net Income) | D7: ='Income Statement'!D25 -> 2078.42 | E7: ='Income Statement'!E25 -> 2519.09 | F7: ='Income Statement'!F25 -> 2533.36 | G7: ='Income Statement'!G25 -> 2837.5 | H7: ='Income Statement'!H25 -> 2812.21 | I7: ='Income Statement'!I25 -> 2462.05 | J7: ='Income Statement'!J25 -> 3152.0952 | K7: ='Income Statement'!K25 -> 3372.7419 | ... N7: ='Income Statement'!N25 -> 4327.727
A8: (+) Depreciation | D8: ='Income Statement'!D18 -> 184.81 | E8: ='Income Statement'!E18 -> 197.85 | F8: ='Income Statement'!F18 -> 200.54 | G8: ='Income Statement'!G18 -> 225.91 | H8: ='Income Statement'!H18 -> 300.46 | I8: ='Income Statement'!I18 -> 313.34 | J8: ='Income Statement'!J18 -> 375.24943 | K8: ='Income Statement'!K18 -> 401.51689 | ... N8: ='Income Statement'!N18 -> 515.20559
A9: – Change in Working Capital | E9: ='Balance Sheet'!E27 -> 88.97 | F9: ='Balance Sheet'!F27 -> 380.19 | G9: ='Balance Sheet'!G27 -> -340.81 | H9: ='Balance Sheet'!H27 -> -126.32 | I9: ='Balance Sheet'!I27 -> -14.18 | J9: ='Balance Sheet'!J27 -> 66.59596 | K9: ='Balance Sheet'!K27 -> -0.035982822 | L9: ='Balance Sheet'!L27 -> -0.044001851 | ... N9: ='Balance Sheet'!N27 -> -0.058273851
A10: – Capex | D10: ='Income Statement'!D5*Assumptions!C10 -> 343.3197 | E10: ='Income Statement'!E5*Assumptions!C10 -> 386.4912 | F10: ='Income Statement'!F5*Assumptions!C10 -> 418.3401 | G10: ='Income Statement'!G5*Assumptions!C10 -> 479.547 | H10: ='Income Statement'!H5*Assumptions!C10 -> 496.3863 | I10: ='Income Statement'!I5*Assumptions!C10 -> 526.0506 | J10: ='Income Statement'!J5*Assumptions!C10 -> 562.87414 | K10: ='Income Statement'!K5*Assumptions!C10 -> 602.27533 | L10: ='Income Statement'!L5*Assumptions!C10 -> 650.45736 | M10: ='Income Statement'!M5*Assumptions!C10 -> 708.99852 | N10: ='Income Statement'!N5*Assumptions!C10 -> 772.80839
A12: Free Cash Flow | D12: =D7+D8-D9-D10 -> 1919.9103 | E12: =E7+E8-E9-E10 -> 2241.4788 | F12: =F7+F8-F9-F10 -> 1935.3699 | G12: =G7+G8-G9-G10 -> 2924.673 | H12: =H7+H8-H9-H10 -> 2742.6037 | I12: =I7+I8-I9-I10 -> 2263.5194 | J12: ='Income Statement'!J25+'Cash Flow'!J8-'Cash Flow'!J9-'Cash Flow'!J10 -> 2897.8745 | K12: =K7+K8-K9-K10 -> 3172.0194 | L12: =L7+L8-L9-L10 -> 3425.7861 | M12: =M7+M8-M9-M10 -> 3734.1123 | N12: =N7+N8-N9-N10 -> 4070.1824
A14: (+) Opening Cash | D14: 81.13 | E14: 789.02 | F14: 762.32 | G14: 1459.43 | H14: 1678.84 | I14: 1771.87 | J14: =I15 -> 4035.3894 | K14: =J15 -> 6933.2639 | L14: =K15 -> 10105.283 | M14: =L15 -> 13531.069 | N14: =M15 -> 17265.182
A15: Closing Cash | D15: =D12+D14 -> 2001.0403 | E15: =E12+E14 -> 3030.4988 | F15: =F12+F14 -> 2697.6899 | G15: =G12+G14 -> 4384.103 | H15: =H12+H14 -> 4421.4437 | I15: =I12+I14 -> 4035.3894 | J15: =J12+J14 -> 6933.2639 | K15: =K12+K14 -> 10105.283 | ... N15: =N12+N14 -> 21335.364

Sheet Balance Sheet
D2: FY 2020 | E2: FY 2021 | F2: FY 2022 | G2: FY 2023 | H2: FY 2024 | I2: FY 2025 | J2: FY 2026 | K2: FY 2027 | L2: FY 2028 | M2: FY 2029 | N2: FY 2030
A3: BALANCE SHEET | D3: 43921 | E3: 44286 | F3: 44651 | G3: 45016 | H3: 45382 | I3: 45747 | J3: 46112 | K3: 46477 | L3: 46843 | M3: 47208 | N3: 47573
A5: Assets
A6: PPE | D6: 1716.37 | E6: 1634.3 | F6: 1584.05 | G6: 2472.19 | H6: 2602.94 | I6: 2734.61 | J6: =I6+'Cash Flow'!J10-'Cash Flow'!J8 -> 2922.2347 | K6: =J6+'Cash Flow'!K10-'Cash Flow'!K8 -> 3122.9932 | L6: =K6+'Cash Flow'!L10-'Cash Flow'!L8 -> 3339.8123 | M6: =L6+'Cash Flow'!M10-'Cash Flow'!M8 -> 3576.1451 | N6: =M6+'Cash Flow'!N10-'Cash Flow'!N8 -> 3833.7479
A7: Inventory | D7: 740.96 | E7: 1091.49 | F7: 1367.49 | G7: 1193.26 | H7: 1181.22 | I7: 1236.51 | J7: ='Income Statement'!J7*(Assumptions!C15/365) -> 1171.4979 | K7: ='Income Statement'!K7*(Assumptions!C15/365) -> 1253.5027 | L7: ='Income Statement'!L7*(Assumptions!C15/365) -> 1353.7829 | M7: ='Income Statement'!M7*(Assumptions!C15/365) -> 1475.6234 | N7: ='Income Statement'!N7*(Assumptions!C15/365) -> 1608.4295
A8: Receivables | D8: 320.36 | E8: 257.27 | F8: 331.93 | G8: 328.94 | H8: 393.33 | I8: 448.61 | J8: ='Income Statement'!J5*(Assumptions!C14/365) -> 462.63628 | K8: ='Income Statement'!K5*(Assumptions!C14/365) -> 495.02082 | L8: ='Income Statement'!L5*(Assumptions!C14/365) -> 534.62249 | M8: ='Income Statement'!M5*(Assumptions!C14/365) -> 582.73851 | N8: ='Income Statement'!N5*(Assumptions!C14/365) -> 635.18498
A9: Other Current + Non-current Assets | D9: =42.46+142.17 -> 184.63 | E9: =105.98+ 122.01 -> 227.99 | F9: =126.34 +99.18 -> 225.52 | G9: =48.56 +180.74 -> 229.3 | H9: =58.68+ 133.71 -> 192.39 | I9: =42.04 +123.98 -> 166.02 | J9: ='Income Statement'!J5*'Balance Sheet'!J10 -> 187.62471 | K9: ='Income Statement'!K5*'Balance Sheet'!K10 -> 200.75844 | L9: ='Income Statement'!L5*'Balance Sheet'!L10 -> 216.81912 | M9: ='Income Statement'!M5*'Balance Sheet'!M10 -> 236.33284 | N9: ='Income Statement'!N5*'Balance Sheet'!N10 -> 257.6028
A10: Other Current + Non-current Assets % | D10: =D9/'Income Statement'!D5 -> 0.016133359 | E10: =E9/'Income Statement'!E5 -> 0.01769691 | F10: =F9/'Income Statement'!F5 -> 0.016172487 | G10: =G9/'Income Statement'!G5 -> 0.014344788 | H10: =H9/'Income Statement'!H5 -> 0.011627436 | I10: =I9/'Income Statement'!I5 -> 0.0094679105 | J10: 0.01 | K10: 0.01 | L10: 0.01 | M10: 0.01 | N10: 0.01
A11: Cash | D11: 81.23 | E11: 142.74 | F11: 117.99 | G11: 102.38 | H11: 322.8 | I11: 132.78 | J11: =I11+'Cash Flow'!J10 -> 695.65414 | K11: =J11+'Cash Flow'!K10 -> 1297.9295 | L11: =K11+'Cash Flow'!L10 -> 1948.3868 | M11: =L11+'Cash Flow'!M10 -> 2657.3854 | N11: =M11+'Cash Flow'!N10 -> 3430.1937
A12: Total Assets | D12: =SUM(D6:D9)+D11 -> 3043.55 | E12: =SUM(E6:E9)+E11 -> 3353.79 | F12: =SUM(F6:F9)+F11 -> 3626.98 | G12: =SUM(G6:G9)+G11 -> 4326.07 | H12: =SUM(H6:H9)+H11 -> 4692.68 | I12: =SUM(I6:I9)+I11 -> 4718.53 | J12: =SUM(J6:J9)+J11 -> 5439.6477 | K12: =SUM(K6:K9)+K11 -> 6370.2046 | ... N12: =SUM(N6:N9)+N11 -> 9765.1589
A14: Liabilities
A15: Debt (Borrowings + Lease) | D15: =766.06+747.99 -> 1514.05 | E15: =747.75+1339.42 -> 2087.17 | F15: =706.99+13.76+1758.55+1.9 -> 2481.2 | G15: =1551.8+14.36+1428.71+2.5 -> 2997.37 | H15: =904.72+20.13+1136.49+3.62 -> 2064.96 | I15: =712.94 +19.45+ 511.83+ 2.29 -> 1246.51 | J15: 1246.51 | K15: 1246.51 | L15: 1246.51 | M15: 1246.51 | N15: 1246.51
A16: Payables | D16: =8.53+1107.75 -> 1116.28 | E16: =28.44+1286.31 -> 1314.75 | F16: =62.76+1222.46 -> 1285.22 | G16: =43.92+1404.89 -> 1448.81 | H16: =30.83+1596.65 -> 1627.48 | I16: =27.83+1724.4 -> 1752.23 | J16: ='Income Statement'!J7*(Assumptions!C16/365) -> 1634.6482 | K16: ='Income Statement'!K7*(Assumptions!C16/365) -> 1749.0736 | L16: ='Income Statement'!L7*(Assumptions!C16/365) -> 1888.9995 | M16: ='Income Statement'!M7*(Assumptions!C16/365) -> 2059.0094 | N16: ='Income Statement'!N7*(Assumptions!C16/365) -> 2244.3202
A17: Other Liabilities | D17: 150.08 | E17: 140.54 | F17: 126.71 | G17: 176.34 | H17: 167.29 | I17: 194.7 | J17: ='Income Statement'!J5*'Balance Sheet'!J18 -> 187.62471 | K17: ='Income Statement'!K5*'Balance Sheet'!K18 -> 200.75844 | L17: ='Income Statement'!L5*'Balance Sheet'!L18 -> 216.81912 | M17: ='Income Statement'!M5*'Balance Sheet'!M18 -> 236.33284 | N17: ='Income Statement'!N5*'Balance Sheet'!N18 -> 257.6028
A18: Other Liabilities % | D18: =D17/'Income Statement'!D5 -> 0.013114307 | E18: =E17/'Income Statement'!E5 -> 0.010908916 | F18: =F17/'Income Statement'!F5 -> 0.0090866259 | G18: =G17/'Income Statement'!G5 -> 0.011031661 | H18: =H17/'Income Statement'!H5 -> 0.010110472 | I18: =I17/'Income Statement'!I5 -> 0.011103495 | J18: 0.01 | K18: 0.01 | L18: 0.01 | M18: 0.01 | N18: 0.01
A19: Total Liabilities | D19: =SUM(D15:D17) -> 2780.41 | E19: =SUM(E15:E17) -> 3542.46 | F19: =SUM(F15:F17) -> 3893.13 | G19: =SUM(G15:G17) -> 4622.52 | H19: =SUM(H15:H17) -> 3859.73 | I19: =SUM(I15:I17) -> 3193.44 | J19: =SUM(J15:J17) -> 3068.7829 | K19: =SUM(K15:K17) -> 3196.342 | ... N19: =SUM(N15:N17) -> 3748.433
A21: Equity
A22: Share Capital (constant) | D22: 24.05 | E22: 24.09 | F22: 24.09 | G22: 24.09 | H22: 24.09 | I22: 24.09 | J22: 24.09 | K22: 24.09 | L22: 24.09 | M22: 24.09 | N22: 24.09
A23: Retained Earnings | D23: 4378.78 | E23: 3523.57 | F23: 2534.01 | G23: 3510.18 | H23: 3917.43 | I23: 4331.63 | J23: =I23+'Income Statement'!J25 -> 7483.7252 | K23: =J23+'Income Statement'!K25 -> 10856.467 | L23: =K23+'Income Statement'!L25 -> 14499.028 | M23: =L23+'Income Statement'!M25 -> 18469.42 | N23: =M23+'Income Statement'!N25 -> 22797.147
A24: Total Equity | D24: =SUM(D22:D23) -> 4402.83 | E24: =SUM(E22:E23) -> 3547.66 | F24: =SUM(F22:F23) -> 2558.1 | G24: =SUM(G22:G23) -> 3534.27 | H24: =SUM(H22:H23) -> 3941.52 | I24: =SUM(I22:I23) -> 4355.72 | J24: =SUM(J22:J23) -> 7507.8152 | K24: =SUM(K22:K23) -> 10880.557 | ... N24: =SUM(N22:N23) -> 22821.237
A26: Working Capital | D26: =D8+D7-D16 -> -54.96 | E26: =E8+E7-E16 -> 34.01 | F26: =F8+F7-F16 -> 414.2 | G26: =G8+G7-G16 -> 73.39 | H26: =H8+H7-H16 -> -52.93 | I26: =I8+I7-I16 -> -67.11 | J26: =J8+J7-J16 -> -0.51404031 | K26: =K8+K7-K16 -> -0.55002313 | ... N26: =N8+N7-N16 -> -0.70576108
A27: Change in Working Cpital | E27: =E26-D26 -> 88.97 | F27: =F26-E26 -> 380.19 | G27: =G26-F26 -> -340.81 | H27: =H26-G26 -> -126.32 | I27: =I26-H26 -> -14.18 | J27: =J26-I26 -> 66.59596 | K27: =K26-J26 -> -0.035982822 | L27: =L26-K26 -> -0.044001851 | ... N27: =N26-M26 -> -0.058273851

Sheet DCF Valution
C2: FY 2026 | D2: FY 2027 | E2: FY 2028 | F2: FY 2029 | G2: FY 2030
A3: DCF VALUATION | C3: 46112 | D3: 46477 | E3: 46843 | F3: 47208 | G3: 47573
A5: FCF | C5: ='Cash Flow'!J12 -> 2897.8745 | D5: ='Cash Flow'!K12 -> 3172.0194 | E5: ='Cash Flow'!L12 -> 3425.7861 | F5: ='Cash Flow'!M12 -> 3734.1123 | G5: ='Cash Flow'!N12 -> 4070.1824
A7: DISCOUNT FACTOR | C7: =1/(1+Assumptions!C12)^1 -> 0.90909091 | D7: =1/(1+Assumptions!C12)^2 -> 0.82644628 | E7: =1/(1+Assumptions!C12)^3 -> 0.7513148 | F7: =1/(1+Assumptions!C12)^4 -> 0.68301346 | G7: =1/(1+Assumptions!C12)^5 -> 0.62092132
A8: PV OF FCF | C8: =C5*C7 -> 2634.4314 | D8: =D5*D7 -> 2621.5036 | E8: =E5*E7 -> 2573.8438 | F8: =F5*F7 -> 2550.449 | G8: =G5*G7 -> 2527.2631
A9: TERMINAL VALUE (TV) | C9: ='Cash Flow'!I12*(1+Assumptions!C13)/(Assumptions!C12-Assumptions!C13) -> 39234.336 | D9: ='Cash Flow'!J12*(1+Assumptions!C13)/(Assumptions!C12-Assumptions!C13) -> 50229.825 | E9: ='Cash Flow'!K12*(1+Assumptions!C13)/(Assumptions!C12-Assumptions!C13) -> 54981.67 | F9: ='Cash Flow'!L12*(1+Assumptions!C13)/(Assumptions!C12-Assumptions!C13) -> 59380.292 | G9: ='Cash Flow'!M12*(1+Assumptions!C13)/(Assumptions!C12-Assumptions!C13) -> 64724.614
A11: PV OF TV | G11: =G9*G7 -> 40188.893
A13: ENTERPRISE VALUE (EV) | G13: =12907.49+G11 -> 53096.383
A15: EQUITY VALUE | G15: =G13+('Balance Sheet'!N15-'Balance Sheet'!N11) -> 50912.699
A17: SHARE PRICE | G17: =G13/24.09 -> 2204.084
